README.md
setup.py
dzy/__init__.py
dzy/dw.py
dzy/keepalive.py
dzy/timer.py
dzy/utils.py
dzy.egg-info/PKG-INFO
dzy.egg-info/SOURCES.txt
dzy.egg-info/dependency_links.txt
dzy.egg-info/requires.txt
dzy.egg-info/top_level.txt
tests/__init__.py
tests/test_keepalive.py
tests/test_timer.py
tests/test_utils.py