Metadata-Version: 1.2
Name: dzy
Version: 1.1.3
Summary: dzy Python package
Home-page: UNKNOWN
Author: dzy
License: UNKNOWN
Platform: UNKNOWN
Requires-Python: >=3.6
